mcafee/__init__.py
mcafee/mcafee.py
mcafee-0.1.0.dist-info/METADATA
mcafee-0.1.0.dist-info/WHEEL
mcafee-0.1.0.dist-info/entry_points.txt
mcafee-0.1.0.dist-info/top_level.txt
mcafee-0.1.0.dist-info/RECORD
