Metadata-Version: 2.1
Name: mcafee
Version: 0.1.0
Summary: Number four automated fee manager script in all of Kazakhstan.
Home-page: https://github.com/yuvadm/mcafee
Author: Yuval Adam
Author-email: _@yuv.al
License: GPLv3
Project-URL: Bug Tracker, https://github.com/yuvadm/mcafee/issues
Platform: UNKNOWN
Classifier: Programming Language :: Python :: 3
Classifier: Development Status :: 5 - Production/Stable
Classifier: License :: OSI Approved :: GNU General Public License v3 (GPLv3)
Classifier: Operating System :: OS Independent
Classifier: Environment :: Console
Requires-Python: >=3.6
Requires-Dist: lndgrpc
Requires-Dist: click
